sonpy/Adc.3
sonpy/AdcMark.3
sonpy/All.3
sonpy/Bad_Param.3
sonpy/Bad_Read.3
sonpy/Bad_Write.3
sonpy/Call_Again.3
sonpy/CanWrite.3
sonpy/ChannelBytes.3
sonpy/ChannelDelete.3
sonpy/ChannelDivide.3
sonpy/ChannelMaxTime.3
sonpy/ChannelType.3
sonpy/ChannelUndelete.3
sonpy/Channel_Type.3
sonpy/Channel_Used.3
sonpy/Clear.3
sonpy/Commit.3
sonpy/CommitFlags.3
sonpy/Corrupt_File.3
sonpy/Data.3
sonpy/DataType.3
sonpy/DeleteBuffer.3
sonpy/DigMark.3
sonpy/EditMarker.3
sonpy/EditRealMark.3
sonpy/EditTextMark.3
sonpy/EditWaveMark.3
sonpy/EmptyFile.3
sonpy/EventBoth.3
sonpy/EventFall.3
sonpy/EventRise.3
sonpy/ExtendMaxTime.3
sonpy/FileSize.3
sonpy/Filter.3
sonpy/FilterMode.3
sonpy/FilterSet.3
sonpy/FilterState.3
sonpy/First.3
sonpy/FirstTime.3
sonpy/FlushSysBuffers.3
sonpy/FlushSystem.3
sonpy/GetAppID.3
sonpy/GetChannelComment.3
sonpy/GetChannelOffset.3
sonpy/GetChannelScale.3
sonpy/GetChannelTitle.3
sonpy/GetChannelUnits.3
sonpy/GetChannelYRange.3
sonpy/GetColumn.3
sonpy/GetErrorString.3
sonpy/GetExMarkInfo.3
sonpy/GetExtraData.3
sonpy/GetExtraDataSize.3
sonpy/GetFileComment.3
sonpy/GetFreeChannel.3
sonpy/GetIdealRate.3
sonpy/GetItem.3
sonpy/GetLayer.3
sonpy/GetMark.3
sonpy/GetMode.3
sonpy/GetName.3
sonpy/GetOpenError.3
sonpy/GetState.3
sonpy/GetString.3
sonpy/GetTimeBase.3
sonpy/GetTimeDate.3
sonpy/GetVersion.3
sonpy/HeaderOnly.3
sonpy/Invert.3
sonpy/IsModified.3
sonpy/IsSaving.3
sonpy/ItemSize.3
sonpy/LatestTime.3
sonpy/MakeFile.py
sonpy/Marker.3
sonpy/MarkerFilter.3
sonpy/MaxChannels.3
sonpy/MaxTime.3
sonpy/MaxTime64.3
sonpy/More_Data.3
sonpy/NoSaveList.3
sonpy/No_Access.3
sonpy/No_Block.3
sonpy/No_Channel.3
sonpy/No_Extra.3
sonpy/No_File.3
sonpy/No_Memory.3
sonpy/None.3
sonpy/Off.3
sonpy/OpenFlags.3
sonpy/Over_Write.3
sonpy/Past_EOF.3
sonpy/Past_SOF.3
sonpy/PhysicalChannel.3
sonpy/PreviousNTime.3
sonpy/ReadEvents.3
sonpy/ReadFile.py
sonpy/ReadMarkers.3
sonpy/ReadRealMarks.3
sonpy/ReadTextMarks.3
sonpy/ReadWave.3
sonpy/ReadWave.py
sonpy/ReadWaveMarks.3
sonpy/Read_Only.3
sonpy-1.9.5.dist-info/METADATA
sonpy-1.9.5.dist-info/WHEEL
sonpy-1.9.5.dist-info/top_level.txt
sonpy-1.9.5.dist-info/RECORD
