Metadata-Version: 2.1
Name: sonpy
Version: 1.9.5
Summary: The Python interface to the 64-bit Son library
Home-page: http://ced.co.uk/downloads/latestsoftware
Author: William Collins
Author-email: will@ced.co.uk
License: UNKNOWN
Platform: UNKNOWN
Requires-Python: >=3.9, <3.10
Requires-Dist: numpy
